fingerprint/__init__.py
fingerprint/entrypoints/__init__.py
fingerprint/entrypoints/cli/__init__.py
fingerprint/entrypoints/cli/main.py
fingerprint/service_layer/__init__.py
fingerprint/service_layer/handlers.py
fingerprint_report_templates/__init__.py
fingerprint_report_templates/fingerprint_report/config-cellar.json
fingerprint_report_templates/fingerprint_report/config.json
fingerprint_report_templates/fingerprint_report/templates/layout.html
fingerprint_report_templates/fingerprint_report/templates/main.html
fingerprint_report_templates/fingerprint_report/templates/prefixes.json
fingerprint_report_templates/fingerprint_report/templates/macros/builders.html
fingerprint_report_templates/fingerprint_report/templates/macros/renderers.html
fingerprint_report_templates/fingerprint_report/templates/macros/selectors.html
rdf_fingerprinter-0.3.1.dist-info/LICENSE
rdf_fingerprinter-0.3.1.dist-info/METADATA
rdf_fingerprinter-0.3.1.dist-info/WHEEL
rdf_fingerprinter-0.3.1.dist-info/entry_points.txt
rdf_fingerprinter-0.3.1.dist-info/top_level.txt
rdf_fingerprinter-0.3.1.dist-info/RECORD
