Metadata-Version: 2.1
Name: rdf-fingerprinter
Version: 0.3.1
Summary: Find out kind of data shapes your RDF dataset instantiates.
Home-page: https://github.com/meaningfy-ws/rdf-fingerprinter
Author: Eugeniu Costetchi
Author-email: costezki.eugen@gmail.com
Maintainer: Eugeniu Costetchi
Maintainer-email: costezki.eugen@gmail.com
License: Apache License 2.0
Keywords: rdf,application profile,data shape,statistics,fingerprint,sparql,linked-data
Platform: any
Classifier: Development Status :: 4 - Beta
Classifier: Programming Language :: Python
Classifier: Programming Language :: Python :: 3
Classifier: Programming Language :: Python :: 3.8
Classifier: Environment :: Console
Classifier: License :: OSI Approved :: Apache Software License
Classifier: Operating System :: OS Independent
Classifier: Topic :: Utilities
Classifier: Topic :: Scientific/Engineering :: Information Analysis
Classifier: Topic :: Software Development :: Libraries
Classifier: Intended Audience :: Developers
Classifier: Intended Audience :: Information Technology
Classifier: Intended Audience :: Science/Research
Classifier: Topic :: Software Development :: Libraries :: Python Modules
Classifier: Natural Language :: English
Requires-Python: >=3.8
License-File: LICENSE
Requires-Dist: eds4jinja2 ~=0.2.0
Requires-Dist: click ~=8.1.7
Requires-Dist: pathlib ~=1.0.1
Requires-Dist: rdflib ~=7.0.0
Requires-Dist: SPARQLWrapper ~=2.0.0
Requires-Dist: importlib-resources ~=6.1.0
Provides-Extra: test
Requires-Dist: pytest ~=7.4.2 ; extra == 'test'
Requires-Dist: coverage ~=7.3.2 ; extra == 'test'
Requires-Dist: pytest-cov ~=4.1.0 ; extra == 'test'
Requires-Dist: pytest-bdd ~=7.0.0 ; extra == 'test'
Requires-Dist: beautifulsoup4 ~=4.12.2 ; extra == 'test'
Requires-Dist: flake8 ~=6.1.0 ; extra == 'test'
Requires-Dist: sphinx ~=7.1.2 ; extra == 'test'
Requires-Dist: recommonmark ~=0.7.1 ; extra == 'test'
Requires-Dist: twine ~=4.0.2 ; extra == 'test'
Requires-Dist: setuptools ~=68.2.2 ; extra == 'test'
Requires-Dist: wheel ~=0.41.2 ; extra == 'test'
